LICENSE
MANIFEST.in
README.md
pyproject.toml
requirements.txt
setup.py
csrc/activation.cpp
csrc/activation_kernels.cu
csrc/attention.cpp
csrc/cache.cpp
csrc/cache_kernels.cu
csrc/cuda_utils.cpp
csrc/cuda_utils_kernels.cu
csrc/dispatch_utils.h
csrc/layernorm.cpp
csrc/layernorm_kernels.cu
csrc/pos_encoding.cpp
csrc/pos_encoding_kernels.cu
csrc/quantization.cpp
csrc/reduction_utils.cuh
csrc/attention/attention_dtypes.h
csrc/attention/attention_generic.cuh
csrc/attention/attention_kernels.cu
csrc/attention/attention_utils.cuh
csrc/attention/dtype_bfloat16.cuh
csrc/attention/dtype_float16.cuh
csrc/attention/dtype_float32.cuh
csrc/quantization/awq/dequantize.cuh
csrc/quantization/awq/gemm_kernels.cu
csrc/quantization/squeezellm/quant_cuda_kernel.cu
tests/test_regression.py
vllm/__init__.py
vllm/block.py
vllm/config.py
vllm/logger.py
vllm/outputs.py
vllm/py.typed
vllm/sampling_params.py
vllm/sequence.py
vllm/utils.py
vllm/core/__init__.py
vllm/core/block_manager.py
vllm/core/policy.py
vllm/core/scheduler.py
vllm/engine/__init__.py
vllm/engine/arg_utils.py
vllm/engine/async_llm_engine.py
vllm/engine/llm_engine.py
vllm/engine/ray_utils.py
vllm/entrypoints/__init__.py
vllm/entrypoints/api_server.py
vllm/entrypoints/llm.py
vllm/entrypoints/openai/__init__.py
vllm/entrypoints/openai/api_server.py
vllm/entrypoints/openai/protocol.py
vllm/model_executor/__init__.py
vllm/model_executor/input_metadata.py
vllm/model_executor/model_loader.py
vllm/model_executor/utils.py
vllm/model_executor/weight_utils.py
vllm/model_executor/layers/__init__.py
vllm/model_executor/layers/activation.py
vllm/model_executor/layers/attention.py
vllm/model_executor/layers/layernorm.py
vllm/model_executor/layers/linear.py
vllm/model_executor/layers/rotary_embedding.py
vllm/model_executor/layers/sampler.py
vllm/model_executor/layers/vocab_parallel_embedding.py
vllm/model_executor/layers/quantization/__init__.py
vllm/model_executor/layers/quantization/awq.py
vllm_cpm.egg-info/PKG-INFO
vllm_cpm.egg-info/SOURCES.txt
vllm_cpm.egg-info/dependency_links.txt
vllm_cpm.egg-info/requires.txt
vllm_cpm.egg-info/top_level.txt