Metadata-Version: 2.1
Name: vllm-cpm
Version: 0.2.2
Summary: A high-throughput and memory-efficient inference and serving engine for LLMs
Author: ModelBest Inc.
License: Apache 2.0
Classifier: Programming Language :: Python :: 3.8
Classifier: Programming Language :: Python :: 3.9
Classifier: Programming Language :: Python :: 3.10
Classifier: Programming Language :: Python :: 3.11
Classifier: License :: OSI Approved :: Apache Software License
Classifier: Topic :: Scientific/Engineering :: Artificial Intelligence
Requires-Python: >=3.8
License-File: LICENSE
Requires-Dist: ninja
Requires-Dist: psutil
Requires-Dist: ray>=2.5.1
Requires-Dist: pandas
Requires-Dist: pyarrow
Requires-Dist: sentencepiece
Requires-Dist: numpy
Requires-Dist: einops
Requires-Dist: torch>=2.1.0
Requires-Dist: transformers>=4.34.0
Requires-Dist: xformers>=0.0.22.post7
Requires-Dist: fastapi
Requires-Dist: uvicorn[standard]
Requires-Dist: pydantic==1.10.13
